{
"type": "FeatureCollection",
"crs": { "type": "name", "properties": { "name": "urn:ogc:def:crs:OGC:1.3:CRS84" } },
                                                                                
"features": [
{ "type": "Feature", "properties": { "FID_": 0.000000, "Shape__": "Point", "name": "Juneau Airport Ground Source Heat Pump", "location": "Juneau", "lon": -134.400000, "lat": 58.300000, "type": "Geothermal", "pro_cost": 1026000.000000, "grant_amou": 513000.000000, "note": null, "label": "Juneau Airport GSHP", "displaceme": 29500.000000, "aedg_id": 10001.000000, "path": "http:\/\/aea.gina.alaska.edu\/pub\/ref2013highlights\/10001Photo.jpg", "summary": "http:\/\/aea.gina.alaska.edu\/pub\/ref2013highlights\/10001_REFSummary.pdf", "globalid": "{4191E710-756C-4CB4-88CE-D8A78B91556B}" }, "geometry": { "type": "Point", "coordinates": [ -134.4, 58.3 ] } }
]
}
